blue_codespace/README.py
blue_codespace/__init__.py
blue_codespace/__main__.py
blue_codespace/config.env
blue_codespace/env.py
blue_codespace/functions.py
blue_codespace/host.py
blue_codespace/logger.py
blue_codespace/sample.env
blue_codespace/urls.py
blue_codespace/.abcli/abcli.sh
blue_codespace/.abcli/actions.sh
blue_codespace/.abcli/alias.sh
blue_codespace/.abcli/blue_codespace.sh
blue_codespace/.abcli/browse.sh
blue_codespace/.abcli/tests/README.sh
blue_codespace/.abcli/tests/help.sh
blue_codespace/.abcli/tests/version.sh
blue_codespace/help/__init__.py
blue_codespace/help/__main__.py
blue_codespace/help/functions.py
blue_codespace-4.200.1.dist-info/LICENSE
blue_codespace-4.200.1.dist-info/METADATA
blue_codespace-4.200.1.dist-info/WHEEL
blue_codespace-4.200.1.dist-info/top_level.txt
blue_codespace-4.200.1.dist-info/RECORD
