Metadata-Version: 2.1
Name: blue_codespace
Version: 4.200.1
Summary: 🌀 a github codespaces terraform.
Home-page: https://github.com/kamangir/blue-codespace
Author: Arash Abadpour (Kamangir)
Author-email: arash@kamangir.net
License: Public Domain
Classifier: Programming Language :: Python :: 3
Classifier: Programming Language :: Unix Shell
Classifier: License :: Public Domain
Classifier: Operating System :: OS Independent
License-File: LICENSE
Requires-Dist: blueness
Requires-Dist: blue-options
Requires-Dist: abcli
Requires-Dist: boto3
Requires-Dist: geojson
Requires-Dist: geopandas
Requires-Dist: matplotlib
Requires-Dist: numpy
Requires-Dist: opencv-python
Requires-Dist: pymysql
Requires-Dist: pyyaml
Requires-Dist: pylint
Requires-Dist: pytest
Requires-Dist: python-dotenv[cli]
Requires-Dist: tqdm
